<?xml version="1.0" encoding="utf-8"?>
<prestashop xmlns:xlink="http://www.w3.org/1999/xlink">
  <product>
    <id/>
    <active>1</active>
    <state>1</state>
    <id_tax_rules_group>1</id_tax_rules_group>
    <id_shop_default>1</id_shop_default>
    <advanced_stock_management>1</advanced_stock_management>
    <price>80.750000</price>
    <name>
      <language id="1">Shield z wyświetlaczem LCD TFT 3,5&quot; z panelem dotykowym do Arduino - Waveshare 13506</language>
      <language id="2">Shield z wyświetlaczem LCD TFT 3,5&quot; z panelem dotykowym do Arduino - Waveshare 13506</language>
    </name>
    <link_rewrite>
      <language id="1">shield-z-wy-wietlaczem-lcd-tft-3-5-z-panelem-dotykowym-do-arduino-waveshare-13506</language>
      <language id="2">shield-z-wy-wietlaczem-lcd-tft-3-5-z-panelem-dotykowym-do-arduino-waveshare-13506</language>
    </link_rewrite>
    <description>
      <language id="1">Shield z wyświetlaczem LCD o przekątnej 3,5 cali z panelem dotykowym. Ekran ma rozdzielczość 480x320 pikseli, a komunikacja odbywa się przez interfejs SPI. Waveshare 3.5inch TFT Touch Shield</language>
      <language id="2">Shield z wyświetlaczem LCD o przekątnej 3,5 cali z panelem dotykowym. Ekran ma rozdzielczość 480x320 pikseli, a komunikacja odbywa się przez interfejs SPI. Waveshare 3.5inch TFT Touch Shield</language>
    </description>
    <description_short>
      <language id="1">Shield z wyświetlaczem LCD o przekątnej 3,5 cali z panelem dotykowym. Ekran ma rozdzielczość 480x320 pikseli, a komunikacja odbywa się przez interfejs SPI. Waveshare 3.5inch TFT Touch Shield</language>
      <language id="2">Shield z wyświetlaczem LCD o przekątnej 3,5 cali z panelem dotykowym. Ekran ma rozdzielczość 480x320 pikseli, a komunikacja odbywa się przez interfejs SPI. Waveshare 3.5inch TFT Touch Shield</language>
    </description_short>
    <meta_keywords>
      <language id="1">test</language>
      <language id="2">test</language>
    </meta_keywords>
    <id_category_default>29</id_category_default>
    <show_price>1</show_price>
    <on_sale>0</on_sale>
    <associations>
      <categories>
        <category>
          <id>29</id>
        </category>
        <category>
          <id>2</id>
        </category>
      </categories>
    </associations>
  </product>
</prestashop>
