<?xml version="1.0" encoding="utf-8"?>
<prestashop xmlns:xlink="http://www.w3.org/1999/xlink">
  <product>
    <id/>
    <active>1</active>
    <state>1</state>
    <id_tax_rules_group>1</id_tax_rules_group>
    <id_shop_default>1</id_shop_default>
    <advanced_stock_management>1</advanced_stock_management>
    <price>206.830000</price>
    <name>
      <language id="1">Moduł sterownika PLC z 14 wyjściami przekaźnikowymi FX3U-30MR</language>
      <language id="2">Moduł sterownika PLC z 14 wyjściami przekaźnikowymi FX3U-30MR</language>
    </name>
    <link_rewrite>
      <language id="1">modu-sterownika-plc-z-14-wyj-ciami-przeka-nikowymi-fx3u-30mr</language>
      <language id="2">modu-sterownika-plc-z-14-wyj-ciami-przeka-nikowymi-fx3u-30mr</language>
    </link_rewrite>
    <description>
      <language id="1">Moduł sterownika PLC FX3U-30MR obsługuje 16 punktów wejściowych i 14 wyjściowych z napięciem zasilania 24 VDC. Oferuje funkcje analogowe, szybkie liczenie, obsługę operacji zmiennoprzecinkowych i ma pojemność 8000 kroków, z opcją podłączenia ekranu tekstowego i dotykowego.</language>
      <language id="2">Moduł sterownika PLC FX3U-30MR obsługuje 16 punktów wejściowych i 14 wyjściowych z napięciem zasilania 24 VDC. Oferuje funkcje analogowe, szybkie liczenie, obsługę operacji zmiennoprzecinkowych i ma pojemność 8000 kroków, z opcją podłączenia ekranu tekstowego i dotykowego.</language>
    </description>
    <description_short>
      <language id="1">Moduł sterownika PLC FX3U-30MR obsługuje 16 punktów wejściowych i 14 wyjściowych z napięciem zasilania 24 VDC. Oferuje funkcje analogowe, szybkie liczenie, obsługę operacji zmiennoprzecinkowych i ma pojemność 8000 kroków, z opcją podłączenia ekranu tekstowego i dotykowego.</language>
      <language id="2">Moduł sterownika PLC FX3U-30MR obsługuje 16 punktów wejściowych i 14 wyjściowych z napięciem zasilania 24 VDC. Oferuje funkcje analogowe, szybkie liczenie, obsługę operacji zmiennoprzecinkowych i ma pojemność 8000 kroków, z opcją podłączenia ekranu tekstowego i dotykowego.</language>
    </description_short>
    <meta_keywords>
      <language id="1">test</language>
      <language id="2">test</language>
    </meta_keywords>
    <id_category_default>55</id_category_default>
    <show_price>1</show_price>
    <on_sale>0</on_sale>
    <associations>
      <categories>
        <category>
          <id>55</id>
        </category>
        <category>
          <id>2</id>
        </category>
      </categories>
    </associations>
  </product>
</prestashop>
