<?xml version="1.0" encoding="utf-8"?>
<prestashop xmlns:xlink="http://www.w3.org/1999/xlink">
  <product>
    <id/>
    <active>1</active>
    <state>1</state>
    <id_tax_rules_group>1</id_tax_rules_group>
    <id_shop_default>1</id_shop_default>
    <advanced_stock_management>1</advanced_stock_management>
    <price>82.800000</price>
    <name>
      <language id="1">iNode Control ID (czerwony) - inteligentny identyfikator RFID</language>
      <language id="2">iNode Control ID (czerwony) - inteligentny identyfikator RFID</language>
    </name>
    <link_rewrite>
      <language id="1">inode-control-id-czerwony-inteligentny-identyfikator-rfid</language>
      <language id="2">inode-control-id-czerwony-inteligentny-identyfikator-rfid</language>
    </link_rewrite>
    <description>
      <language id="1">Inteligentny identyfikator RFID współpracujący z iNode Control Point</language>
      <language id="2">Inteligentny identyfikator RFID współpracujący z iNode Control Point</language>
    </description>
    <description_short>
      <language id="1">Inteligentny identyfikator RFID współpracujący z iNode Control Point</language>
      <language id="2">Inteligentny identyfikator RFID współpracujący z iNode Control Point</language>
    </description_short>
    <meta_keywords>
      <language id="1">test</language>
      <language id="2">test</language>
    </meta_keywords>
    <id_category_default>38</id_category_default>
    <show_price>1</show_price>
    <on_sale>0</on_sale>
    <associations>
      <categories>
        <category>
          <id>38</id>
        </category>
        <category>
          <id>2</id>
        </category>
      </categories>
    </associations>
  </product>
</prestashop>
